{
    "doctor": [
        {
            "id": 1,
            "first_name": "Nashaat Alarbed",
            "last_name": "fahed",
            "description": "fahedfahedfahedfahed",
            "locale": "en",
            "is_active": 1,
            "is_approved": 1,
            "image": "fafaffafa",
            "social_media_id": 1,
            "clinic_id": 1,
            "appointments_id": 5,
            "specialty_id": 1,
            "hospital_id": 1,
            "created_at": null,
            "updated_at": null,
            "socialmedia": {
                "phone_number": 1234568,
                "whatsapp_number": 1234569,
                "facebook_account": "www.facebook.com",
                "instagram_account": "FFgdgxgfcFFFFF",
                "telegram_number": 124587,
                "email": "one@gmail.com",
                "doctor_id": 9,
                "is_active": 0
            },
            "clinic": {
                "name": "hghgkj",
                "is_active": 1,
                "is_approved": 1,
                "location_id": 1,
                "doctor_id": 1,
                "phone_number": 1236598,
                "active_times_id": 1,
                "created_at": null,
                "updated_at": null
            },
            "medical file": {
                "customer_id": 9,
                "file_number": 9,
                "file_date": "2021-05-19",
                "review_date": "2021-05-20",
                "PDF": "pdf2",
                "doctor_id": 9,
                "is_active": 1,
                "is_approved": 1,
                "created_at": null,
                "updated_at": null
            },
            "active time": {
                "start_time": "19:56:17",
                "end_time": "19:56:17",
                "is_active": 1,
                "is_approved": 1,
                "created_at": null,
                "updated_at": null
            },
            "create customer by doctor": {
                "doctor_id": 1,
                "customer_id": 2,
                "medical_file_id": 1,
                "age": 14,
                "note": "djnksdsa",
                "social_status": "single",
                "gender": "male",
                "blood_type": "A+",
                "is_active": 1,
                "is_approved": 0
            },
            "medicaldevice": [
                {
                    "id": 1,
                    "name": "image",
                    "description": "dfnsdknvfksd",
                    "locale": "en",
                    "is_active": 1,
                    "is_approved": 1,
                    "doctor_id": 1,
                    "hospital_id": 1,
                    "created_at": null,
                    "updated_at": null
                },
                {
                    "id": 2,
                    "name": "image",
                    "description": "dfnsdknvfksd",
                    "locale": "en",
                    "is_active": 1,
                    "is_approved": 1,
                    "doctor_id": 1,
                    "hospital_id": 1,
                    "created_at": null,
                    "updated_at": null
                },
                {
                    "id": 3,
                    "name": "image",
                    "description": "dfnsdknvfksd",
                    "locale": "en",
                    "is_active": 1,
                    "is_approved": 1,
                    "doctor_id": 1,
                    "hospital_id": 1,
                    "created_at": null,
                    "updated_at": null
                },
                {
                    "id": 4,
                    "name": "image",
                    "description": "dfnsdknvfksd",
                    "locale": "en",
                    "is_active": 1,
                    "is_approved": 1,
                    "doctor_id": 1,
                    "hospital_id": 1,
                    "created_at": null,
                    "updated_at": null
                },
                {
                    "id": 5,
                    "name": "image",
                    "description": "dfnsdknvfksd",
                    "locale": "en",
                    "is_active": 1,
                    "is_approved": 1,
                    "doctor_id": 1,
                    "hospital_id": 1,
                    "created_at": null,
                    "updated_at": null
                },
                {
                    "id": 6,
                    "name": "image",
                    "description": "dfnsdknvfksd",
                    "locale": "en",
                    "is_active": 1,
                    "is_approved": 1,
                    "doctor_id": 1,
                    "hospital_id": 1,
                    "created_at": null,
                    "updated_at": null
                }
            ],
            "specialty": [
                {
                    "id": 1,
                    "name": "dream",
                    "description": "dreamdreamdreamdream",
                    "locale": "en",
                    "is_active": 1,
                    "graduation_year": 1236,
                    "created_at": null,
                    "updated_at": null
                },
                {
                    "id": 2,
                    "name": "dream",
                    "description": "dreamdreamdreamdream",
                    "locale": "en",
                    "is_active": 1,
                    "graduation_year": 1236,
                    "created_at": null,
                    "updated_at": null
                },
                {
                    "id": 3,
                    "name": "dream",
                    "description": "dreamdreamdreamdream",
                    "locale": "en",
                    "is_active": 1,
                    "graduation_year": 1236,
                    "created_at": null,
                    "updated_at": null
                },
                {
                    "id": 4,
                    "name": "dream",
                    "description": "dreamdreamdreamdream",
                    "locale": "en",
                    "is_active": 1,
                    "graduation_year": 1236,
                    "created_at": null,
                    "updated_at": null
                },
                {
                    "id": 5,
                    "name": "dream",
                    "description": "dreamdreamdreamdream",
                    "locale": "en",
                    "is_active": 1,
                    "graduation_year": 1236,
                    "created_at": null,
                    "updated_at": null
                },
                {
                    "id": 6,
                    "name": "dream",
                    "description": "dreamdreamdreamdream",
                    "locale": "en",
                    "is_active": 1,
                    "graduation_year": 1236,
                    "created_at": null,
                    "updated_at": null
                }
            ],
            "appointment": [
                {
                    "id": 1,
                    "description": "dreamdreamdreamdream",
                    "locale": "en",
                    "doctor_id": 11,
                    "customer_id": 11,
                    "active_times_id": 2,
                    "morning_evening": 0,
                    "is_approved": 0,
                    "is_active": 0
                },
                {
                    "id": 2,
                    "description": "dreamdreamdreamdream",
                    "locale": "en",
                    "doctor_id": 11,
                    "customer_id": 11,
                    "active_times_id": 2,
                    "morning_evening": 0,
                    "is_approved": 0,
                    "is_active": 0
                },
                {
                    "id": 3,
                    "description": "dreamdreamdreamdream",
                    "locale": "en",
                    "doctor_id": 11,
                    "customer_id": 11,
                    "active_times_id": 2,
                    "morning_evening": 0,
                    "is_approved": 0,
                    "is_active": 0
                },
                {
                    "id": 4,
                    "description": "dreamdreamdreamdream",
                    "locale": "en",
                    "doctor_id": 11,
                    "customer_id": 11,
                    "active_times_id": 2,
                    "morning_evening": 0,
                    "is_approved": 0,
                    "is_active": 0
                },
                {
                    "id": 5,
                    "description": "dreamdreamdreamdream",
                    "locale": "en",
                    "doctor_id": 11,
                    "customer_id": 11,
                    "active_times_id": 2,
                    "morning_evening": 0,
                    "is_approved": 0,
                    "is_active": 0
                },
                {
                    "id": 6,
                    "description": "dreamdreamdreamdream",
                    "locale": "en",
                    "doctor_id": 11,
                    "customer_id": 11,
                    "active_times_id": 2,
                    "morning_evening": 0,
                    "is_approved": 0,
                    "is_active": 0
                }
            ],
            "customer": [
                {
                    "id": 1,
                    "first_name": "asdasd",
                    "last_name": "asd",
                    "address": "asdasdfcxdsds",
                    "locale": "en",
                    "is_active": 0,
                    "is_approved": 1,
                    "social_media_id": 15,
                    "created_at": null,
                    "updated_at": null
                },
                {
                    "id": 2,
                    "first_name": "asdasd",
                    "last_name": "asd",
                    "address": "asdasdfcxdsds",
                    "locale": "en",
                    "is_active": 0,
                    "is_approved": 1,
                    "social_media_id": 15,
                    "created_at": null,
                    "updated_at": null
                },
                {
                    "id": 3,
                    "first_name": "asdasd",
                    "last_name": "asd",
                    "address": "asdasdfcxdsds",
                    "locale": "en",
                    "is_active": 0,
                    "is_approved": 1,
                    "social_media_id": 15,
                    "created_at": null,
                    "updated_at": null
                },
                {
                    "id": 4,
                    "first_name": "asdasd",
                    "last_name": "asd",
                    "address": "asdasdfcxdsds",
                    "locale": "en",
                    "is_active": 0,
                    "is_approved": 1,
                    "social_media_id": 15,
                    "created_at": null,
                    "updated_at": null
                },
                {
                    "id": 5,
                    "first_name": "asdasd",
                    "last_name": "asd",
                    "address": "asdasdfcxdsds",
                    "locale": "en",
                    "is_active": 0,
                    "is_approved": 1,
                    "social_media_id": 15,
                    "created_at": null,
                    "updated_at": null
                },
                {
                    "id": 6,
                    "first_name": "asdasd",
                    "last_name": "asd",
                    "address": "asdasdfcxdsds",
                    "locale": "en",
                    "is_active": 0,
                    "is_approved": 1,
                    "social_media_id": 15,
                    "created_at": null,
                    "updated_at": null
                }
            ],
            "hospital": [
                {
                    "id": 1,
                    "name": "image",
                    "description": "dfnsdknvfksd",
                    "locale": "en",
                    "is_active": 1,
                    "is_approved": 1,
                    "doctor_id": 1,
                    "general_hospital": 1,
                    "private_hospital": 0,
                    "location_id": 1,
                    "created_at": null,
                    "updated_at": null
                },
                {
                    "id": 2,
                    "name": "image",
                    "description": "dfnsdknvfksd",
                    "locale": "en",
                    "is_active": 1,
                    "is_approved": 1,
                    "doctor_id": 1,
                    "general_hospital": 1,
                    "private_hospital": 0,
                    "location_id": 1,
                    "created_at": null,
                    "updated_at": null
                },
                {
                    "id": 3,
                    "name": "image",
                    "description": "dfnsdknvfksd",
                    "locale": "en",
                    "is_active": 1,
                    "is_approved": 1,
                    "doctor_id": 1,
                    "general_hospital": 1,
                    "private_hospital": 0,
                    "location_id": 1,
                    "created_at": null,
                    "updated_at": null
                },
                {
                    "id": 4,
                    "name": "image",
                    "description": "dfnsdknvfksd",
                    "locale": "en",
                    "is_active": 1,
                    "is_approved": 1,
                    "doctor_id": 1,
                    "general_hospital": 1,
                    "private_hospital": 0,
                    "location_id": 1,
                    "created_at": null,
                    "updated_at": null
                },
                {
                    "id": 5,
                    "name": "image",
                    "description": "dfnsdknvfksd",
                    "locale": "en",
                    "is_active": 1,
                    "is_approved": 1,
                    "doctor_id": 1,
                    "general_hospital": 1,
                    "private_hospital": 0,
                    "location_id": 1,
                    "created_at": null,
                    "updated_at": null
                },
                {
                    "id": 6,
                    "name": "image",
                    "description": "dfnsdknvfksd",
                    "locale": "en",
                    "is_active": 1,
                    "is_approved": 1,
                    "doctor_id": 1,
                    "general_hospital": 1,
                    "private_hospital": 0,
                    "location_id": 1,
                    "created_at": null,
                    "updated_at": null
                }
            ]
        },
        {
            "id": 2,
            "first_name": "Walaa jamool",
            "last_name": "fahed",
            "description": "fahedfahedfahedfahed",
            "locale": "en",
            "is_active": 1,
            "is_approved": 1,
            "image": "fafaffafa",
            "social_media_id": 1,
            "clinic_id": 1,
            "appointments_id": 5,
            "specialty_id": 1,
            "hospital_id": 1,
            "created_at": null,
            "updated_at": null,
            "socialmedia": {
                "phone_number": 1234568,
                "whatsapp_number": 1234569,
                "facebook_account": "www.facebook.com",
                "instagram_account": "FFgdgxgfcFFFFF",
                "telegram_number": 124587,
                "email": "one@gmail.com",
                "doctor_id": 9,
                "is_active": 0
            },
            "clinic": {
                "name": "hghgkj",
                "is_active": 1,
                "is_approved": 1,
                "location_id": 1,
                "doctor_id": 1,
                "phone_number": 1236598,
                "active_times_id": 1,
                "created_at": null,
                "updated_at": null
            },
            "medical file": {
                "customer_id": 9,
                "file_number": 9,
                "file_date": "2021-05-19",
                "review_date": "2021-05-20",
                "PDF": "pdf2",
                "doctor_id": 9,
                "is_active": 1,
                "is_approved": 1,
                "created_at": null,
                "updated_at": null
            },
            "active time": {
                "start_time": "19:56:17",
                "end_time": "19:56:17",
                "is_active": 1,
                "is_approved": 1,
                "created_at": null,
                "updated_at": null
            },
            "create customer by doctor": {
                "doctor_id": 1,
                "customer_id": 2,
                "medical_file_id": 1,
                "age": 14,
                "note": "djnksdsa",
                "social_status": "single",
                "gender": "male",
                "blood_type": "A+",
                "is_active": 1,
                "is_approved": 0
            },
            "medicaldevice": [
                {
                    "id": 1,
                    "name": "image",
                    "description": "dfnsdknvfksd",
                    "locale": "en",
                    "is_active": 1,
                    "is_approved": 1,
                    "doctor_id": 1,
                    "hospital_id": 1,
                    "created_at": null,
                    "updated_at": null
                },
                {
                    "id": 2,
                    "name": "image",
                    "description": "dfnsdknvfksd",
                    "locale": "en",
                    "is_active": 1,
                    "is_approved": 1,
                    "doctor_id": 1,
                    "hospital_id": 1,
                    "created_at": null,
                    "updated_at": null
                },
                {
                    "id": 3,
                    "name": "image",
                    "description": "dfnsdknvfksd",
                    "locale": "en",
                    "is_active": 1,
                    "is_approved": 1,
                    "doctor_id": 1,
                    "hospital_id": 1,
                    "created_at": null,
                    "updated_at": null
                },
                {
                    "id": 4,
                    "name": "image",
                    "description": "dfnsdknvfksd",
                    "locale": "en",
                    "is_active": 1,
                    "is_approved": 1,
                    "doctor_id": 1,
                    "hospital_id": 1,
                    "created_at": null,
                    "updated_at": null
                },
                {
                    "id": 5,
                    "name": "image",
                    "description": "dfnsdknvfksd",
                    "locale": "en",
                    "is_active": 1,
                    "is_approved": 1,
                    "doctor_id": 1,
                    "hospital_id": 1,
                    "created_at": null,
                    "updated_at": null
                },
                {
                    "id": 6,
                    "name": "image",
                    "description": "dfnsdknvfksd",
                    "locale": "en",
                    "is_active": 1,
                    "is_approved": 1,
                    "doctor_id": 1,
                    "hospital_id": 1,
                    "created_at": null,
                    "updated_at": null
                }
            ],
            "specialty": [
                {
                    "id": 1,
                    "name": "dream",
                    "description": "dreamdreamdreamdream",
                    "locale": "en",
                    "is_active": 1,
                    "graduation_year": 1236,
                    "created_at": null,
                    "updated_at": null
                },
                {
                    "id": 2,
                    "name": "dream",
                    "description": "dreamdreamdreamdream",
                    "locale": "en",
                    "is_active": 1,
                    "graduation_year": 1236,
                    "created_at": null,
                    "updated_at": null
                },
                {
                    "id": 3,
                    "name": "dream",
                    "description": "dreamdreamdreamdream",
                    "locale": "en",
                    "is_active": 1,
                    "graduation_year": 1236,
                    "created_at": null,
                    "updated_at": null
                },
                {
                    "id": 4,
                    "name": "dream",
                    "description": "dreamdreamdreamdream",
                    "locale": "en",
                    "is_active": 1,
                    "graduation_year": 1236,
                    "created_at": null,
                    "updated_at": null
                },
                {
                    "id": 5,
                    "name": "dream",
                    "description": "dreamdreamdreamdream",
                    "locale": "en",
                    "is_active": 1,
                    "graduation_year": 1236,
                    "created_at": null,
                    "updated_at": null
                },
                {
                    "id": 6,
                    "name": "dream",
                    "description": "dreamdreamdreamdream",
                    "locale": "en",
                    "is_active": 1,
                    "graduation_year": 1236,
                    "created_at": null,
                    "updated_at": null
                }
            ],
            "appointment": [
                {
                    "id": 1,
                    "description": "dreamdreamdreamdream",
                    "locale": "en",
                    "doctor_id": 11,
                    "customer_id": 11,
                    "active_times_id": 2,
                    "morning_evening": 0,
                    "is_approved": 0,
                    "is_active": 0
                },
                {
                    "id": 2,
                    "description": "dreamdreamdreamdream",
                    "locale": "en",
                    "doctor_id": 11,
                    "customer_id": 11,
                    "active_times_id": 2,
                    "morning_evening": 0,
                    "is_approved": 0,
                    "is_active": 0
                },
                {
                    "id": 3,
                    "description": "dreamdreamdreamdream",
                    "locale": "en",
                    "doctor_id": 11,
                    "customer_id": 11,
                    "active_times_id": 2,
                    "morning_evening": 0,
                    "is_approved": 0,
                    "is_active": 0
                },
                {
                    "id": 4,
                    "description": "dreamdreamdreamdream",
                    "locale": "en",
                    "doctor_id": 11,
                    "customer_id": 11,
                    "active_times_id": 2,
                    "morning_evening": 0,
                    "is_approved": 0,
                    "is_active": 0
                },
                {
                    "id": 5,
                    "description": "dreamdreamdreamdream",
                    "locale": "en",
                    "doctor_id": 11,
                    "customer_id": 11,
                    "active_times_id": 2,
                    "morning_evening": 0,
                    "is_approved": 0,
                    "is_active": 0
                },
                {
                    "id": 6,
                    "description": "dreamdreamdreamdream",
                    "locale": "en",
                    "doctor_id": 11,
                    "customer_id": 11,
                    "active_times_id": 2,
                    "morning_evening": 0,
                    "is_approved": 0,
                    "is_active": 0
                }
            ],
            "customer": [
                {
                    "id": 1,
                    "first_name": "asdasd",
                    "last_name": "asd",
                    "address": "asdasdfcxdsds",
                    "locale": "en",
                    "is_active": 0,
                    "is_approved": 1,
                    "social_media_id": 15,
                    "created_at": null,
                    "updated_at": null
                },
                {
                    "id": 2,
                    "first_name": "asdasd",
                    "last_name": "asd",
                    "address": "asdasdfcxdsds",
                    "locale": "en",
                    "is_active": 0,
                    "is_approved": 1,
                    "social_media_id": 15,
                    "created_at": null,
                    "updated_at": null
                },
                {
                    "id": 3,
                    "first_name": "asdasd",
                    "last_name": "asd",
                    "address": "asdasdfcxdsds",
                    "locale": "en",
                    "is_active": 0,
                    "is_approved": 1,
                    "social_media_id": 15,
                    "created_at": null,
                    "updated_at": null
                },
                {
                    "id": 4,
                    "first_name": "asdasd",
                    "last_name": "asd",
                    "address": "asdasdfcxdsds",
                    "locale": "en",
                    "is_active": 0,
                    "is_approved": 1,
                    "social_media_id": 15,
                    "created_at": null,
                    "updated_at": null
                },
                {
                    "id": 5,
                    "first_name": "asdasd",
                    "last_name": "asd",
                    "address": "asdasdfcxdsds",
                    "locale": "en",
                    "is_active": 0,
                    "is_approved": 1,
                    "social_media_id": 15,
                    "created_at": null,
                    "updated_at": null
                },
                {
                    "id": 6,
                    "first_name": "asdasd",
                    "last_name": "asd",
                    "address": "asdasdfcxdsds",
                    "locale": "en",
                    "is_active": 0,
                    "is_approved": 1,
                    "social_media_id": 15,
                    "created_at": null,
                    "updated_at": null
                }
            ],
            "hospital": [
                {
                    "id": 1,
                    "name": "image",
                    "description": "dfnsdknvfksd",
                    "locale": "en",
                    "is_active": 1,
                    "is_approved": 1,
                    "doctor_id": 1,
                    "general_hospital": 1,
                    "private_hospital": 0,
                    "location_id": 1,
                    "created_at": null,
                    "updated_at": null
                },
                {
                    "id": 2,
                    "name": "image",
                    "description": "dfnsdknvfksd",
                    "locale": "en",
                    "is_active": 1,
                    "is_approved": 1,
                    "doctor_id": 1,
                    "general_hospital": 1,
                    "private_hospital": 0,
                    "location_id": 1,
                    "created_at": null,
                    "updated_at": null
                },
                {
                    "id": 3,
                    "name": "image",
                    "description": "dfnsdknvfksd",
                    "locale": "en",
                    "is_active": 1,
                    "is_approved": 1,
                    "doctor_id": 1,
                    "general_hospital": 1,
                    "private_hospital": 0,
                    "location_id": 1,
                    "created_at": null,
                    "updated_at": null
                },
                {
                    "id": 4,
                    "name": "image",
                    "description": "dfnsdknvfksd",
                    "locale": "en",
                    "is_active": 1,
                    "is_approved": 1,
                    "doctor_id": 1,
                    "general_hospital": 1,
                    "private_hospital": 0,
                    "location_id": 1,
                    "created_at": null,
                    "updated_at": null
                },
                {
                    "id": 5,
                    "name": "image",
                    "description": "dfnsdknvfksd",
                    "locale": "en",
                    "is_active": 1,
                    "is_approved": 1,
                    "doctor_id": 1,
                    "general_hospital": 1,
                    "private_hospital": 0,
                    "location_id": 1,
                    "created_at": null,
                    "updated_at": null
                },
                {
                    "id": 6,
                    "name": "image",
                    "description": "dfnsdknvfksd",
                    "locale": "en",
                    "is_active": 1,
                    "is_approved": 1,
                    "doctor_id": 1,
                    "general_hospital": 1,
                    "private_hospital": 0,
                    "location_id": 1,
                    "created_at": null,
                    "updated_at": null
                }
            ]
        },
        {
            "id": 3,
            "first_name": "Hassan alhakem",
            "last_name": "fahed",
            "description": "fahedfahedfahedfahed",
            "locale": "en",
            "is_active": 1,
            "is_approved": 1,
            "image": "fafaffafa",
            "social_media_id": 1,
            "clinic_id": 1,
            "appointments_id": 5,
            "specialty_id": 1,
            "hospital_id": 1,
            "created_at": null,
            "updated_at": null,
            "socialmedia": {
                "phone_number": 1234568,
                "whatsapp_number": 1234569,
                "facebook_account": "www.facebook.com",
                "instagram_account": "FFgdgxgfcFFFFF",
                "telegram_number": 124587,
                "email": "one@gmail.com",
                "doctor_id": 9,
                "is_active": 0
            },
            "clinic": {
                "name": "hghgkj",
                "is_active": 1,
                "is_approved": 1,
                "location_id": 1,
                "doctor_id": 1,
                "phone_number": 1236598,
                "active_times_id": 1,
                "created_at": null,
                "updated_at": null
            },
            "medical file": {
                "customer_id": 9,
                "file_number": 9,
                "file_date": "2021-05-19",
                "review_date": "2021-05-20",
                "PDF": "pdf2",
                "doctor_id": 9,
                "is_active": 1,
                "is_approved": 1,
                "created_at": null,
                "updated_at": null
            },
            "active time": {
                "start_time": "19:56:17",
                "end_time": "19:56:17",
                "is_active": 1,
                "is_approved": 1,
                "created_at": null,
                "updated_at": null
            },
            "create customer by doctor": {
                "doctor_id": 1,
                "customer_id": 2,
                "medical_file_id": 1,
                "age": 14,
                "note": "djnksdsa",
                "social_status": "single",
                "gender": "male",
                "blood_type": "A+",
                "is_active": 1,
                "is_approved": 0
            },
            "medicaldevice": [
                {
                    "id": 1,
                    "name": "image",
                    "description": "dfnsdknvfksd",
                    "locale": "en",
                    "is_active": 1,
                    "is_approved": 1,
                    "doctor_id": 1,
                    "hospital_id": 1,
                    "created_at": null,
                    "updated_at": null
                },
                {
                    "id": 2,
                    "name": "image",
                    "description": "dfnsdknvfksd",
                    "locale": "en",
                    "is_active": 1,
                    "is_approved": 1,
                    "doctor_id": 1,
                    "hospital_id": 1,
                    "created_at": null,
                    "updated_at": null
                },
                {
                    "id": 3,
                    "name": "image",
                    "description": "dfnsdknvfksd",
                    "locale": "en",
                    "is_active": 1,
                    "is_approved": 1,
                    "doctor_id": 1,
                    "hospital_id": 1,
                    "created_at": null,
                    "updated_at": null
                },
                {
                    "id": 4,
                    "name": "image",
                    "description": "dfnsdknvfksd",
                    "locale": "en",
                    "is_active": 1,
                    "is_approved": 1,
                    "doctor_id": 1,
                    "hospital_id": 1,
                    "created_at": null,
                    "updated_at": null
                },
                {
                    "id": 5,
                    "name": "image",
                    "description": "dfnsdknvfksd",
                    "locale": "en",
                    "is_active": 1,
                    "is_approved": 1,
                    "doctor_id": 1,
                    "hospital_id": 1,
                    "created_at": null,
                    "updated_at": null
                },
                {
                    "id": 6,
                    "name": "image",
                    "description": "dfnsdknvfksd",
                    "locale": "en",
                    "is_active": 1,
                    "is_approved": 1,
                    "doctor_id": 1,
                    "hospital_id": 1,
                    "created_at": null,
                    "updated_at": null
                }
            ],
            "specialty": [
                {
                    "id": 1,
                    "name": "dream",
                    "description": "dreamdreamdreamdream",
                    "locale": "en",
                    "is_active": 1,
                    "graduation_year": 1236,
                    "created_at": null,
                    "updated_at": null
                },
                {
                    "id": 2,
                    "name": "dream",
                    "description": "dreamdreamdreamdream",
                    "locale": "en",
                    "is_active": 1,
                    "graduation_year": 1236,
                    "created_at": null,
                    "updated_at": null
                },
                {
                    "id": 3,
                    "name": "dream",
                    "description": "dreamdreamdreamdream",
                    "locale": "en",
                    "is_active": 1,
                    "graduation_year": 1236,
                    "created_at": null,
                    "updated_at": null
                },
                {
                    "id": 4,
                    "name": "dream",
                    "description": "dreamdreamdreamdream",
                    "locale": "en",
                    "is_active": 1,
                    "graduation_year": 1236,
                    "created_at": null,
                    "updated_at": null
                },
                {
                    "id": 5,
                    "name": "dream",
                    "description": "dreamdreamdreamdream",
                    "locale": "en",
                    "is_active": 1,
                    "graduation_year": 1236,
                    "created_at": null,
                    "updated_at": null
                },
                {
                    "id": 6,
                    "name": "dream",
                    "description": "dreamdreamdreamdream",
                    "locale": "en",
                    "is_active": 1,
                    "graduation_year": 1236,
                    "created_at": null,
                    "updated_at": null
                }
            ],
            "appointment": [
                {
                    "id": 1,
                    "description": "dreamdreamdreamdream",
                    "locale": "en",
                    "doctor_id": 11,
                    "customer_id": 11,
                    "active_times_id": 2,
                    "morning_evening": 0,
                    "is_approved": 0,
                    "is_active": 0
                },
                {
                    "id": 2,
                    "description": "dreamdreamdreamdream",
                    "locale": "en",
                    "doctor_id": 11,
                    "customer_id": 11,
                    "active_times_id": 2,
                    "morning_evening": 0,
                    "is_approved": 0,
                    "is_active": 0
                },
                {
                    "id": 3,
                    "description": "dreamdreamdreamdream",
                    "locale": "en",
                    "doctor_id": 11,
                    "customer_id": 11,
                    "active_times_id": 2,
                    "morning_evening": 0,
                    "is_approved": 0,
                    "is_active": 0
                },
                {
                    "id": 4,
                    "description": "dreamdreamdreamdream",
                    "locale": "en",
                    "doctor_id": 11,
                    "customer_id": 11,
                    "active_times_id": 2,
                    "morning_evening": 0,
                    "is_approved": 0,
                    "is_active": 0
                },
                {
                    "id": 5,
                    "description": "dreamdreamdreamdream",
                    "locale": "en",
                    "doctor_id": 11,
                    "customer_id": 11,
                    "active_times_id": 2,
                    "morning_evening": 0,
                    "is_approved": 0,
                    "is_active": 0
                },
                {
                    "id": 6,
                    "description": "dreamdreamdreamdream",
                    "locale": "en",
                    "doctor_id": 11,
                    "customer_id": 11,
                    "active_times_id": 2,
                    "morning_evening": 0,
                    "is_approved": 0,
                    "is_active": 0
                }
            ],
            "customer": [
                {
                    "id": 1,
                    "first_name": "asdasd",
                    "last_name": "asd",
                    "address": "asdasdfcxdsds",
                    "locale": "en",
                    "is_active": 0,
                    "is_approved": 1,
                    "social_media_id": 15,
                    "created_at": null,
                    "updated_at": null
                },
                {
                    "id": 2,
                    "first_name": "asdasd",
                    "last_name": "asd",
                    "address": "asdasdfcxdsds",
                    "locale": "en",
                    "is_active": 0,
                    "is_approved": 1,
                    "social_media_id": 15,
                    "created_at": null,
                    "updated_at": null
                },
                {
                    "id": 3,
                    "first_name": "asdasd",
                    "last_name": "asd",
                    "address": "asdasdfcxdsds",
                    "locale": "en",
                    "is_active": 0,
                    "is_approved": 1,
                    "social_media_id": 15,
                    "created_at": null,
                    "updated_at": null
                },
                {
                    "id": 4,
                    "first_name": "asdasd",
                    "last_name": "asd",
                    "address": "asdasdfcxdsds",
                    "locale": "en",
                    "is_active": 0,
                    "is_approved": 1,
                    "social_media_id": 15,
                    "created_at": null,
                    "updated_at": null
                },
                {
                    "id": 5,
                    "first_name": "asdasd",
                    "last_name": "asd",
                    "address": "asdasdfcxdsds",
                    "locale": "en",
                    "is_active": 0,
                    "is_approved": 1,
                    "social_media_id": 15,
                    "created_at": null,
                    "updated_at": null
                },
                {
                    "id": 6,
                    "first_name": "asdasd",
                    "last_name": "asd",
                    "address": "asdasdfcxdsds",
                    "locale": "en",
                    "is_active": 0,
                    "is_approved": 1,
                    "social_media_id": 15,
                    "created_at": null,
                    "updated_at": null
                }
            ],
            "hospital": [
                {
                    "id": 1,
                    "name": "image",
                    "description": "dfnsdknvfksd",
                    "locale": "en",
                    "is_active": 1,
                    "is_approved": 1,
                    "doctor_id": 1,
                    "general_hospital": 1,
                    "private_hospital": 0,
                    "location_id": 1,
                    "created_at": null,
                    "updated_at": null
                },
                {
                    "id": 2,
                    "name": "image",
                    "description": "dfnsdknvfksd",
                    "locale": "en",
                    "is_active": 1,
                    "is_approved": 1,
                    "doctor_id": 1,
                    "general_hospital": 1,
                    "private_hospital": 0,
                    "location_id": 1,
                    "created_at": null,
                    "updated_at": null
                },
                {
                    "id": 3,
                    "name": "image",
                    "description": "dfnsdknvfksd",
                    "locale": "en",
                    "is_active": 1,
                    "is_approved": 1,
                    "doctor_id": 1,
                    "general_hospital": 1,
                    "private_hospital": 0,
                    "location_id": 1,
                    "created_at": null,
                    "updated_at": null
                },
                {
                    "id": 4,
                    "name": "image",
                    "description": "dfnsdknvfksd",
                    "locale": "en",
                    "is_active": 1,
                    "is_approved": 1,
                    "doctor_id": 1,
                    "general_hospital": 1,
                    "private_hospital": 0,
                    "location_id": 1,
                    "created_at": null,
                    "updated_at": null
                },
                {
                    "id": 5,
                    "name": "image",
                    "description": "dfnsdknvfksd",
                    "locale": "en",
                    "is_active": 1,
                    "is_approved": 1,
                    "doctor_id": 1,
                    "general_hospital": 1,
                    "private_hospital": 0,
                    "location_id": 1,
                    "created_at": null,
                    "updated_at": null
                },
                {
                    "id": 6,
                    "name": "image",
                    "description": "dfnsdknvfksd",
                    "locale": "en",
                    "is_active": 1,
                    "is_approved": 1,
                    "doctor_id": 1,
                    "general_hospital": 1,
                    "private_hospital": 0,
                    "location_id": 1,
                    "created_at": null,
                    "updated_at": null
                }
            ]
        },
        {
            "id": 5,
            "first_name": "Khaled Alshofii",
            "last_name": "fahed",
            "description": "fahedfahedfahedfahed",
            "locale": "en",
            "is_active": 1,
            "is_approved": 1,
            "image": "fafaffafa",
            "social_media_id": 1,
            "clinic_id": 1,
            "appointments_id": 5,
            "specialty_id": 1,
            "hospital_id": 1,
            "created_at": null,
            "updated_at": null,
            "socialmedia": {
                "phone_number": 1234568,
                "whatsapp_number": 1234569,
                "facebook_account": "www.facebook.com",
                "instagram_account": "FFgdgxgfcFFFFF",
                "telegram_number": 124587,
                "email": "one@gmail.com",
                "doctor_id": 9,
                "is_active": 0
            },
            "clinic": {
                "name": "hghgkj",
                "is_active": 1,
                "is_approved": 1,
                "location_id": 1,
                "doctor_id": 1,
                "phone_number": 1236598,
                "active_times_id": 1,
                "created_at": null,
                "updated_at": null
            },
            "medical file": {
                "customer_id": 9,
                "file_number": 9,
                "file_date": "2021-05-19",
                "review_date": "2021-05-20",
                "PDF": "pdf2",
                "doctor_id": 9,
                "is_active": 1,
                "is_approved": 1,
                "created_at": null,
                "updated_at": null
            },
            "active time": {
                "start_time": "19:56:17",
                "end_time": "19:56:17",
                "is_active": 1,
                "is_approved": 1,
                "created_at": null,
                "updated_at": null
            },
            "create customer by doctor": {
                "doctor_id": 1,
                "customer_id": 2,
                "medical_file_id": 1,
                "age": 14,
                "note": "djnksdsa",
                "social_status": "single",
                "gender": "male",
                "blood_type": "A+",
                "is_active": 1,
                "is_approved": 0
            },
            "medicaldevice": [
                {
                    "id": 1,
                    "name": "image",
                    "description": "dfnsdknvfksd",
                    "locale": "en",
                    "is_active": 1,
                    "is_approved": 1,
                    "doctor_id": 1,
                    "hospital_id": 1,
                    "created_at": null,
                    "updated_at": null
                },
                {
                    "id": 2,
                    "name": "image",
                    "description": "dfnsdknvfksd",
                    "locale": "en",
                    "is_active": 1,
                    "is_approved": 1,
                    "doctor_id": 1,
                    "hospital_id": 1,
                    "created_at": null,
                    "updated_at": null
                },
                {
                    "id": 3,
                    "name": "image",
                    "description": "dfnsdknvfksd",
                    "locale": "en",
                    "is_active": 1,
                    "is_approved": 1,
                    "doctor_id": 1,
                    "hospital_id": 1,
                    "created_at": null,
                    "updated_at": null
                },
                {
                    "id": 4,
                    "name": "image",
                    "description": "dfnsdknvfksd",
                    "locale": "en",
                    "is_active": 1,
                    "is_approved": 1,
                    "doctor_id": 1,
                    "hospital_id": 1,
                    "created_at": null,
                    "updated_at": null
                },
                {
                    "id": 5,
                    "name": "image",
                    "description": "dfnsdknvfksd",
                    "locale": "en",
                    "is_active": 1,
                    "is_approved": 1,
                    "doctor_id": 1,
                    "hospital_id": 1,
                    "created_at": null,
                    "updated_at": null
                },
                {
                    "id": 6,
                    "name": "image",
                    "description": "dfnsdknvfksd",
                    "locale": "en",
                    "is_active": 1,
                    "is_approved": 1,
                    "doctor_id": 1,
                    "hospital_id": 1,
                    "created_at": null,
                    "updated_at": null
                }
            ],
            "specialty": [
                {
                    "id": 1,
                    "name": "dream",
                    "description": "dreamdreamdreamdream",
                    "locale": "en",
                    "is_active": 1,
                    "graduation_year": 1236,
                    "created_at": null,
                    "updated_at": null
                },
                {
                    "id": 2,
                    "name": "dream",
                    "description": "dreamdreamdreamdream",
                    "locale": "en",
                    "is_active": 1,
                    "graduation_year": 1236,
                    "created_at": null,
                    "updated_at": null
                },
                {
                    "id": 3,
                    "name": "dream",
                    "description": "dreamdreamdreamdream",
                    "locale": "en",
                    "is_active": 1,
                    "graduation_year": 1236,
                    "created_at": null,
                    "updated_at": null
                },
                {
                    "id": 4,
                    "name": "dream",
                    "description": "dreamdreamdreamdream",
                    "locale": "en",
                    "is_active": 1,
                    "graduation_year": 1236,
                    "created_at": null,
                    "updated_at": null
                },
                {
                    "id": 5,
                    "name": "dream",
                    "description": "dreamdreamdreamdream",
                    "locale": "en",
                    "is_active": 1,
                    "graduation_year": 1236,
                    "created_at": null,
                    "updated_at": null
                },
                {
                    "id": 6,
                    "name": "dream",
                    "description": "dreamdreamdreamdream",
                    "locale": "en",
                    "is_active": 1,
                    "graduation_year": 1236,
                    "created_at": null,
                    "updated_at": null
                }
            ],
            "appointment": [
                {
                    "id": 1,
                    "description": "dreamdreamdreamdream",
                    "locale": "en",
                    "doctor_id": 11,
                    "customer_id": 11,
                    "active_times_id": 2,
                    "morning_evening": 0,
                    "is_approved": 0,
                    "is_active": 0
                },
                {
                    "id": 2,
                    "description": "dreamdreamdreamdream",
                    "locale": "en",
                    "doctor_id": 11,
                    "customer_id": 11,
                    "active_times_id": 2,
                    "morning_evening": 0,
                    "is_approved": 0,
                    "is_active": 0
                },
                {
                    "id": 3,
                    "description": "dreamdreamdreamdream",
                    "locale": "en",
                    "doctor_id": 11,
                    "customer_id": 11,
                    "active_times_id": 2,
                    "morning_evening": 0,
                    "is_approved": 0,
                    "is_active": 0
                },
                {
                    "id": 4,
                    "description": "dreamdreamdreamdream",
                    "locale": "en",
                    "doctor_id": 11,
                    "customer_id": 11,
                    "active_times_id": 2,
                    "morning_evening": 0,
                    "is_approved": 0,
                    "is_active": 0
                },
                {
                    "id": 5,
                    "description": "dreamdreamdreamdream",
                    "locale": "en",
                    "doctor_id": 11,
                    "customer_id": 11,
                    "active_times_id": 2,
                    "morning_evening": 0,
                    "is_approved": 0,
                    "is_active": 0
                },
                {
                    "id": 6,
                    "description": "dreamdreamdreamdream",
                    "locale": "en",
                    "doctor_id": 11,
                    "customer_id": 11,
                    "active_times_id": 2,
                    "morning_evening": 0,
                    "is_approved": 0,
                    "is_active": 0
                }
            ],
            "customer": [
                {
                    "id": 1,
                    "first_name": "asdasd",
                    "last_name": "asd",
                    "address": "asdasdfcxdsds",
                    "locale": "en",
                    "is_active": 0,
                    "is_approved": 1,
                    "social_media_id": 15,
                    "created_at": null,
                    "updated_at": null
                },
                {
                    "id": 2,
                    "first_name": "asdasd",
                    "last_name": "asd",
                    "address": "asdasdfcxdsds",
                    "locale": "en",
                    "is_active": 0,
                    "is_approved": 1,
                    "social_media_id": 15,
                    "created_at": null,
                    "updated_at": null
                },
                {
                    "id": 3,
                    "first_name": "asdasd",
                    "last_name": "asd",
                    "address": "asdasdfcxdsds",
                    "locale": "en",
                    "is_active": 0,
                    "is_approved": 1,
                    "social_media_id": 15,
                    "created_at": null,
                    "updated_at": null
                },
                {
                    "id": 4,
                    "first_name": "asdasd",
                    "last_name": "asd",
                    "address": "asdasdfcxdsds",
                    "locale": "en",
                    "is_active": 0,
                    "is_approved": 1,
                    "social_media_id": 15,
                    "created_at": null,
                    "updated_at": null
                },
                {
                    "id": 5,
                    "first_name": "asdasd",
                    "last_name": "asd",
                    "address": "asdasdfcxdsds",
                    "locale": "en",
                    "is_active": 0,
                    "is_approved": 1,
                    "social_media_id": 15,
                    "created_at": null,
                    "updated_at": null
                },
                {
                    "id": 6,
                    "first_name": "asdasd",
                    "last_name": "asd",
                    "address": "asdasdfcxdsds",
                    "locale": "en",
                    "is_active": 0,
                    "is_approved": 1,
                    "social_media_id": 15,
                    "created_at": null,
                    "updated_at": null
                }
            ],
            "hospital": [
                {
                    "id": 1,
                    "name": "image",
                    "description": "dfnsdknvfksd",
                    "locale": "en",
                    "is_active": 1,
                    "is_approved": 1,
                    "doctor_id": 1,
                    "general_hospital": 1,
                    "private_hospital": 0,
                    "location_id": 1,
                    "created_at": null,
                    "updated_at": null
                },
                {
                    "id": 2,
                    "name": "image",
                    "description": "dfnsdknvfksd",
                    "locale": "en",
                    "is_active": 1,
                    "is_approved": 1,
                    "doctor_id": 1,
                    "general_hospital": 1,
                    "private_hospital": 0,
                    "location_id": 1,
                    "created_at": null,
                    "updated_at": null
                },
                {
                    "id": 3,
                    "name": "image",
                    "description": "dfnsdknvfksd",
                    "locale": "en",
                    "is_active": 1,
                    "is_approved": 1,
                    "doctor_id": 1,
                    "general_hospital": 1,
                    "private_hospital": 0,
                    "location_id": 1,
                    "created_at": null,
                    "updated_at": null
                },
                {
                    "id": 4,
                    "name": "image",
                    "description": "dfnsdknvfksd",
                    "locale": "en",
                    "is_active": 1,
                    "is_approved": 1,
                    "doctor_id": 1,
                    "general_hospital": 1,
                    "private_hospital": 0,
                    "location_id": 1,
                    "created_at": null,
                    "updated_at": null
                },
                {
                    "id": 5,
                    "name": "image",
                    "description": "dfnsdknvfksd",
                    "locale": "en",
                    "is_active": 1,
                    "is_approved": 1,
                    "doctor_id": 1,
                    "general_hospital": 1,
                    "private_hospital": 0,
                    "location_id": 1,
                    "created_at": null,
                    "updated_at": null
                },
                {
                    "id": 6,
                    "name": "image",
                    "description": "dfnsdknvfksd",
                    "locale": "en",
                    "is_active": 1,
                    "is_approved": 1,
                    "doctor_id": 1,
                    "general_hospital": 1,
                    "private_hospital": 0,
                    "location_id": 1,
                    "created_at": null,
                    "updated_at": null
                }
            ]
        },
        {
            "id": 6,
            "first_name": "Samer saaeb",
            "last_name": "fahed",
            "description": "fahedfahedfahedfahed",
            "locale": "en",
            "is_active": 1,
            "is_approved": 1,
            "image": "fafaffafa",
            "social_media_id": 1,
            "clinic_id": 1,
            "appointments_id": 5,
            "specialty_id": 1,
            "hospital_id": 1,
            "created_at": null,
            "updated_at": null,
            "socialmedia": {
                "phone_number": 1234568,
                "whatsapp_number": 1234569,
                "facebook_account": "www.facebook.com",
                "instagram_account": "FFgdgxgfcFFFFF",
                "telegram_number": 124587,
                "email": "one@gmail.com",
                "doctor_id": 9,
                "is_active": 0
            },
            "clinic": {
                "name": "hghgkj",
                "is_active": 1,
                "is_approved": 1,
                "location_id": 1,
                "doctor_id": 1,
                "phone_number": 1236598,
                "active_times_id": 1,
                "created_at": null,
                "updated_at": null
            },
            "medical file": {
                "customer_id": 9,
                "file_number": 9,
                "file_date": "2021-05-19",
                "review_date": "2021-05-20",
                "PDF": "pdf2",
                "doctor_id": 9,
                "is_active": 1,
                "is_approved": 1,
                "created_at": null,
                "updated_at": null
            },
            "active time": {
                "start_time": "19:56:17",
                "end_time": "19:56:17",
                "is_active": 1,
                "is_approved": 1,
                "created_at": null,
                "updated_at": null
            },
            "create customer by doctor": {
                "doctor_id": 1,
                "customer_id": 2,
                "medical_file_id": 1,
                "age": 14,
                "note": "djnksdsa",
                "social_status": "single",
                "gender": "male",
                "blood_type": "A+",
                "is_active": 1,
                "is_approved": 0
            },
            "medicaldevice": [
                {
                    "id": 1,
                    "name": "image",
                    "description": "dfnsdknvfksd",
                    "locale": "en",
                    "is_active": 1,
                    "is_approved": 1,
                    "doctor_id": 1,
                    "hospital_id": 1,
                    "created_at": null,
                    "updated_at": null
                },
                {
                    "id": 2,
                    "name": "image",
                    "description": "dfnsdknvfksd",
                    "locale": "en",
                    "is_active": 1,
                    "is_approved": 1,
                    "doctor_id": 1,
                    "hospital_id": 1,
                    "created_at": null,
                    "updated_at": null
                },
                {
                    "id": 3,
                    "name": "image",
                    "description": "dfnsdknvfksd",
                    "locale": "en",
                    "is_active": 1,
                    "is_approved": 1,
                    "doctor_id": 1,
                    "hospital_id": 1,
                    "created_at": null,
                    "updated_at": null
                },
                {
                    "id": 4,
                    "name": "image",
                    "description": "dfnsdknvfksd",
                    "locale": "en",
                    "is_active": 1,
                    "is_approved": 1,
                    "doctor_id": 1,
                    "hospital_id": 1,
                    "created_at": null,
                    "updated_at": null
                },
                {
                    "id": 5,
                    "name": "image",
                    "description": "dfnsdknvfksd",
                    "locale": "en",
                    "is_active": 1,
                    "is_approved": 1,
                    "doctor_id": 1,
                    "hospital_id": 1,
                    "created_at": null,
                    "updated_at": null
                },
                {
                    "id": 6,
                    "name": "image",
                    "description": "dfnsdknvfksd",
                    "locale": "en",
                    "is_active": 1,
                    "is_approved": 1,
                    "doctor_id": 1,
                    "hospital_id": 1,
                    "created_at": null,
                    "updated_at": null
                }
            ],
            "specialty": [
                {
                    "id": 1,
                    "name": "dream",
                    "description": "dreamdreamdreamdream",
                    "locale": "en",
                    "is_active": 1,
                    "graduation_year": 1236,
                    "created_at": null,
                    "updated_at": null
                },
                {
                    "id": 2,
                    "name": "dream",
                    "description": "dreamdreamdreamdream",
                    "locale": "en",
                    "is_active": 1,
                    "graduation_year": 1236,
                    "created_at": null,
                    "updated_at": null
                },
                {
                    "id": 3,
                    "name": "dream",
                    "description": "dreamdreamdreamdream",
                    "locale": "en",
                    "is_active": 1,
                    "graduation_year": 1236,
                    "created_at": null,
                    "updated_at": null
                },
                {
                    "id": 4,
                    "name": "dream",
                    "description": "dreamdreamdreamdream",
                    "locale": "en",
                    "is_active": 1,
                    "graduation_year": 1236,
                    "created_at": null,
                    "updated_at": null
                },
                {
                    "id": 5,
                    "name": "dream",
                    "description": "dreamdreamdreamdream",
                    "locale": "en",
                    "is_active": 1,
                    "graduation_year": 1236,
                    "created_at": null,
                    "updated_at": null
                },
                {
                    "id": 6,
                    "name": "dream",
                    "description": "dreamdreamdreamdream",
                    "locale": "en",
                    "is_active": 1,
                    "graduation_year": 1236,
                    "created_at": null,
                    "updated_at": null
                }
            ],
            "appointment": [
                {
                    "id": 1,
                    "description": "dreamdreamdreamdream",
                    "locale": "en",
                    "doctor_id": 11,
                    "customer_id": 11,
                    "active_times_id": 2,
                    "morning_evening": 0,
                    "is_approved": 0,
                    "is_active": 0
                },
                {
                    "id": 2,
                    "description": "dreamdreamdreamdream",
                    "locale": "en",
                    "doctor_id": 11,
                    "customer_id": 11,
                    "active_times_id": 2,
                    "morning_evening": 0,
                    "is_approved": 0,
                    "is_active": 0
                },
                {
                    "id": 3,
                    "description": "dreamdreamdreamdream",
                    "locale": "en",
                    "doctor_id": 11,
                    "customer_id": 11,
                    "active_times_id": 2,
                    "morning_evening": 0,
                    "is_approved": 0,
                    "is_active": 0
                },
                {
                    "id": 4,
                    "description": "dreamdreamdreamdream",
                    "locale": "en",
                    "doctor_id": 11,
                    "customer_id": 11,
                    "active_times_id": 2,
                    "morning_evening": 0,
                    "is_approved": 0,
                    "is_active": 0
                },
                {
                    "id": 5,
                    "description": "dreamdreamdreamdream",
                    "locale": "en",
                    "doctor_id": 11,
                    "customer_id": 11,
                    "active_times_id": 2,
                    "morning_evening": 0,
                    "is_approved": 0,
                    "is_active": 0
                },
                {
                    "id": 6,
                    "description": "dreamdreamdreamdream",
                    "locale": "en",
                    "doctor_id": 11,
                    "customer_id": 11,
                    "active_times_id": 2,
                    "morning_evening": 0,
                    "is_approved": 0,
                    "is_active": 0
                }
            ],
            "customer": [
                {
                    "id": 1,
                    "first_name": "asdasd",
                    "last_name": "asd",
                    "address": "asdasdfcxdsds",
                    "locale": "en",
                    "is_active": 0,
                    "is_approved": 1,
                    "social_media_id": 15,
                    "created_at": null,
                    "updated_at": null
                },
                {
                    "id": 2,
                    "first_name": "asdasd",
                    "last_name": "asd",
                    "address": "asdasdfcxdsds",
                    "locale": "en",
                    "is_active": 0,
                    "is_approved": 1,
                    "social_media_id": 15,
                    "created_at": null,
                    "updated_at": null
                },
                {
                    "id": 3,
                    "first_name": "asdasd",
                    "last_name": "asd",
                    "address": "asdasdfcxdsds",
                    "locale": "en",
                    "is_active": 0,
                    "is_approved": 1,
                    "social_media_id": 15,
                    "created_at": null,
                    "updated_at": null
                },
                {
                    "id": 4,
                    "first_name": "asdasd",
                    "last_name": "asd",
                    "address": "asdasdfcxdsds",
                    "locale": "en",
                    "is_active": 0,
                    "is_approved": 1,
                    "social_media_id": 15,
                    "created_at": null,
                    "updated_at": null
                },
                {
                    "id": 5,
                    "first_name": "asdasd",
                    "last_name": "asd",
                    "address": "asdasdfcxdsds",
                    "locale": "en",
                    "is_active": 0,
                    "is_approved": 1,
                    "social_media_id": 15,
                    "created_at": null,
                    "updated_at": null
                },
                {
                    "id": 6,
                    "first_name": "asdasd",
                    "last_name": "asd",
                    "address": "asdasdfcxdsds",
                    "locale": "en",
                    "is_active": 0,
                    "is_approved": 1,
                    "social_media_id": 15,
                    "created_at": null,
                    "updated_at": null
                }
            ],
            "hospital": [
                {
                    "id": 1,
                    "name": "image",
                    "description": "dfnsdknvfksd",
                    "locale": "en",
                    "is_active": 1,
                    "is_approved": 1,
                    "doctor_id": 1,
                    "general_hospital": 1,
                    "private_hospital": 0,
                    "location_id": 1,
                    "created_at": null,
                    "updated_at": null
                },
                {
                    "id": 2,
                    "name": "image",
                    "description": "dfnsdknvfksd",
                    "locale": "en",
                    "is_active": 1,
                    "is_approved": 1,
                    "doctor_id": 1,
                    "general_hospital": 1,
                    "private_hospital": 0,
                    "location_id": 1,
                    "created_at": null,
                    "updated_at": null
                },
                {
                    "id": 3,
                    "name": "image",
                    "description": "dfnsdknvfksd",
                    "locale": "en",
                    "is_active": 1,
                    "is_approved": 1,
                    "doctor_id": 1,
                    "general_hospital": 1,
                    "private_hospital": 0,
                    "location_id": 1,
                    "created_at": null,
                    "updated_at": null
                },
                {
                    "id": 4,
                    "name": "image",
                    "description": "dfnsdknvfksd",
                    "locale": "en",
                    "is_active": 1,
                    "is_approved": 1,
                    "doctor_id": 1,
                    "general_hospital": 1,
                    "private_hospital": 0,
                    "location_id": 1,
                    "created_at": null,
                    "updated_at": null
                },
                {
                    "id": 5,
                    "name": "image",
                    "description": "dfnsdknvfksd",
                    "locale": "en",
                    "is_active": 1,
                    "is_approved": 1,
                    "doctor_id": 1,
                    "general_hospital": 1,
                    "private_hospital": 0,
                    "location_id": 1,
                    "created_at": null,
                    "updated_at": null
                },
                {
                    "id": 6,
                    "name": "image",
                    "description": "dfnsdknvfksd",
                    "locale": "en",
                    "is_active": 1,
                    "is_approved": 1,
                    "doctor_id": 1,
                    "general_hospital": 1,
                    "private_hospital": 0,
                    "location_id": 1,
                    "created_at": null,
                    "updated_at": null
                }
            ]
        },
        {
            "id": 1,
            "first_name": "asdasd",
            "last_name": "fahed",
            "description": "fahedfahedfahedfahed",
            "locale": "en",
            "is_active": 1,
            "is_approved": 1,
            "image": "fafaffafa",
            "social_media_id": 1,
            "clinic_id": 1,
            "appointments_id": 5,
            "specialty_id": 1,
            "hospital_id": 1,
            "created_at": null,
            "updated_at": null,
            "socialmedia": {
                "phone_number": 1234568,
                "whatsapp_number": 1234569,
                "facebook_account": "www.facebook.com",
                "instagram_account": "FFgdgxgfcFFFFF",
                "telegram_number": 124587,
                "email": "one@gmail.com",
                "doctor_id": 9,
                "is_active": 0
            },
            "clinic": {
                "name": "hghgkj",
                "is_active": 1,
                "is_approved": 1,
                "location_id": 1,
                "doctor_id": 1,
                "phone_number": 1236598,
                "active_times_id": 1,
                "created_at": null,
                "updated_at": null
            },
            "medical file": {
                "customer_id": 9,
                "file_number": 9,
                "file_date": "2021-05-19",
                "review_date": "2021-05-20",
                "PDF": "pdf2",
                "doctor_id": 9,
                "is_active": 1,
                "is_approved": 1,
                "created_at": null,
                "updated_at": null
            },
            "active time": {
                "start_time": "19:56:17",
                "end_time": "19:56:17",
                "is_active": 1,
                "is_approved": 1,
                "created_at": null,
                "updated_at": null
            },
            "create customer by doctor": {
                "doctor_id": 1,
                "customer_id": 2,
                "medical_file_id": 1,
                "age": 14,
                "note": "djnksdsa",
                "social_status": "single",
                "gender": "male",
                "blood_type": "A+",
                "is_active": 1,
                "is_approved": 0
            },
            "medicaldevice": [
                {
                    "id": 1,
                    "name": "image",
                    "description": "dfnsdknvfksd",
                    "locale": "en",
                    "is_active": 1,
                    "is_approved": 1,
                    "doctor_id": 1,
                    "hospital_id": 1,
                    "created_at": null,
                    "updated_at": null
                },
                {
                    "id": 2,
                    "name": "image",
                    "description": "dfnsdknvfksd",
                    "locale": "en",
                    "is_active": 1,
                    "is_approved": 1,
                    "doctor_id": 1,
                    "hospital_id": 1,
                    "created_at": null,
                    "updated_at": null
                },
                {
                    "id": 3,
                    "name": "image",
                    "description": "dfnsdknvfksd",
                    "locale": "en",
                    "is_active": 1,
                    "is_approved": 1,
                    "doctor_id": 1,
                    "hospital_id": 1,
                    "created_at": null,
                    "updated_at": null
                },
                {
                    "id": 4,
                    "name": "image",
                    "description": "dfnsdknvfksd",
                    "locale": "en",
                    "is_active": 1,
                    "is_approved": 1,
                    "doctor_id": 1,
                    "hospital_id": 1,
                    "created_at": null,
                    "updated_at": null
                },
                {
                    "id": 5,
                    "name": "image",
                    "description": "dfnsdknvfksd",
                    "locale": "en",
                    "is_active": 1,
                    "is_approved": 1,
                    "doctor_id": 1,
                    "hospital_id": 1,
                    "created_at": null,
                    "updated_at": null
                },
                {
                    "id": 6,
                    "name": "image",
                    "description": "dfnsdknvfksd",
                    "locale": "en",
                    "is_active": 1,
                    "is_approved": 1,
                    "doctor_id": 1,
                    "hospital_id": 1,
                    "created_at": null,
                    "updated_at": null
                }
            ],
            "specialty": [
                {
                    "id": 1,
                    "name": "dream",
                    "description": "dreamdreamdreamdream",
                    "locale": "en",
                    "is_active": 1,
                    "graduation_year": 1236,
                    "created_at": null,
                    "updated_at": null
                },
                {
                    "id": 2,
                    "name": "dream",
                    "description": "dreamdreamdreamdream",
                    "locale": "en",
                    "is_active": 1,
                    "graduation_year": 1236,
                    "created_at": null,
                    "updated_at": null
                },
                {
                    "id": 3,
                    "name": "dream",
                    "description": "dreamdreamdreamdream",
                    "locale": "en",
                    "is_active": 1,
                    "graduation_year": 1236,
                    "created_at": null,
                    "updated_at": null
                },
                {
                    "id": 4,
                    "name": "dream",
                    "description": "dreamdreamdreamdream",
                    "locale": "en",
                    "is_active": 1,
                    "graduation_year": 1236,
                    "created_at": null,
                    "updated_at": null
                },
                {
                    "id": 5,
                    "name": "dream",
                    "description": "dreamdreamdreamdream",
                    "locale": "en",
                    "is_active": 1,
                    "graduation_year": 1236,
                    "created_at": null,
                    "updated_at": null
                },
                {
                    "id": 6,
                    "name": "dream",
                    "description": "dreamdreamdreamdream",
                    "locale": "en",
                    "is_active": 1,
                    "graduation_year": 1236,
                    "created_at": null,
                    "updated_at": null
                }
            ],
            "appointment": [
                {
                    "id": 1,
                    "description": "dreamdreamdreamdream",
                    "locale": "en",
                    "doctor_id": 11,
                    "customer_id": 11,
                    "active_times_id": 2,
                    "morning_evening": 0,
                    "is_approved": 0,
                    "is_active": 0
                },
                {
                    "id": 2,
                    "description": "dreamdreamdreamdream",
                    "locale": "en",
                    "doctor_id": 11,
                    "customer_id": 11,
                    "active_times_id": 2,
                    "morning_evening": 0,
                    "is_approved": 0,
                    "is_active": 0
                },
                {
                    "id": 3,
                    "description": "dreamdreamdreamdream",
                    "locale": "en",
                    "doctor_id": 11,
                    "customer_id": 11,
                    "active_times_id": 2,
                    "morning_evening": 0,
                    "is_approved": 0,
                    "is_active": 0
                },
                {
                    "id": 4,
                    "description": "dreamdreamdreamdream",
                    "locale": "en",
                    "doctor_id": 11,
                    "customer_id": 11,
                    "active_times_id": 2,
                    "morning_evening": 0,
                    "is_approved": 0,
                    "is_active": 0
                },
                {
                    "id": 5,
                    "description": "dreamdreamdreamdream",
                    "locale": "en",
                    "doctor_id": 11,
                    "customer_id": 11,
                    "active_times_id": 2,
                    "morning_evening": 0,
                    "is_approved": 0,
                    "is_active": 0
                },
                {
                    "id": 6,
                    "description": "dreamdreamdreamdream",
                    "locale": "en",
                    "doctor_id": 11,
                    "customer_id": 11,
                    "active_times_id": 2,
                    "morning_evening": 0,
                    "is_approved": 0,
                    "is_active": 0
                }
            ],
            "customer": [
                {
                    "id": 1,
                    "first_name": "asdasd",
                    "last_name": "asd",
                    "address": "asdasdfcxdsds",
                    "locale": "en",
                    "is_active": 0,
                    "is_approved": 1,
                    "social_media_id": 15,
                    "created_at": null,
                    "updated_at": null
                },
                {
                    "id": 2,
                    "first_name": "asdasd",
                    "last_name": "asd",
                    "address": "asdasdfcxdsds",
                    "locale": "en",
                    "is_active": 0,
                    "is_approved": 1,
                    "social_media_id": 15,
                    "created_at": null,
                    "updated_at": null
                },
                {
                    "id": 3,
                    "first_name": "asdasd",
                    "last_name": "asd",
                    "address": "asdasdfcxdsds",
                    "locale": "en",
                    "is_active": 0,
                    "is_approved": 1,
                    "social_media_id": 15,
                    "created_at": null,
                    "updated_at": null
                },
                {
                    "id": 4,
                    "first_name": "asdasd",
                    "last_name": "asd",
                    "address": "asdasdfcxdsds",
                    "locale": "en",
                    "is_active": 0,
                    "is_approved": 1,
                    "social_media_id": 15,
                    "created_at": null,
                    "updated_at": null
                },
                {
                    "id": 5,
                    "first_name": "asdasd",
                    "last_name": "asd",
                    "address": "asdasdfcxdsds",
                    "locale": "en",
                    "is_active": 0,
                    "is_approved": 1,
                    "social_media_id": 15,
                    "created_at": null,
                    "updated_at": null
                },
                {
                    "id": 6,
                    "first_name": "asdasd",
                    "last_name": "asd",
                    "address": "asdasdfcxdsds",
                    "locale": "en",
                    "is_active": 0,
                    "is_approved": 1,
                    "social_media_id": 15,
                    "created_at": null,
                    "updated_at": null
                }
            ],
            "hospital": [
                {
                    "id": 1,
                    "name": "image",
                    "description": "dfnsdknvfksd",
                    "locale": "en",
                    "is_active": 1,
                    "is_approved": 1,
                    "doctor_id": 1,
                    "general_hospital": 1,
                    "private_hospital": 0,
                    "location_id": 1,
                    "created_at": null,
                    "updated_at": null
                },
                {
                    "id": 2,
                    "name": "image",
                    "description": "dfnsdknvfksd",
                    "locale": "en",
                    "is_active": 1,
                    "is_approved": 1,
                    "doctor_id": 1,
                    "general_hospital": 1,
                    "private_hospital": 0,
                    "location_id": 1,
                    "created_at": null,
                    "updated_at": null
                },
                {
                    "id": 3,
                    "name": "image",
                    "description": "dfnsdknvfksd",
                    "locale": "en",
                    "is_active": 1,
                    "is_approved": 1,
                    "doctor_id": 1,
                    "general_hospital": 1,
                    "private_hospital": 0,
                    "location_id": 1,
                    "created_at": null,
                    "updated_at": null
                },
                {
                    "id": 4,
                    "name": "image",
                    "description": "dfnsdknvfksd",
                    "locale": "en",
                    "is_active": 1,
                    "is_approved": 1,
                    "doctor_id": 1,
                    "general_hospital": 1,
                    "private_hospital": 0,
                    "location_id": 1,
                    "created_at": null,
                    "updated_at": null
                },
                {
                    "id": 5,
                    "name": "image",
                    "description": "dfnsdknvfksd",
                    "locale": "en",
                    "is_active": 1,
                    "is_approved": 1,
                    "doctor_id": 1,
                    "general_hospital": 1,
                    "private_hospital": 0,
                    "location_id": 1,
                    "created_at": null,
                    "updated_at": null
                },
                {
                    "id": 6,
                    "name": "image",
                    "description": "dfnsdknvfksd",
                    "locale": "en",
                    "is_active": 1,
                    "is_approved": 1,
                    "doctor_id": 1,
                    "general_hospital": 1,
                    "private_hospital": 0,
                    "location_id": 1,
                    "created_at": null,
                    "updated_at": null
                }
            ]
        }
    ],
    "//commit": "category",
    "medicaldevice": [
        {
            "id": 1,
            "name": "image"
        },
        {
            "id": 2,
            "name": "image"
        },
        {
            "id": 3,
            "name": "image"
        },
        {
            "id": 4,
            "name": "image"
        },
        {
            "id": 5,
            "name": "image"
        },
        {
            "id": 6,
            "name": "image"
        }
    ],
    "hospital": [
        {
            "id": 1,
            "name": "image",
            "description": "dfnsdknvfksd",
            "locale": "en",
            "is_active": 1,
            "is_approved": 1,
            "doctor_id": 1,
            "general_hospital": 1,
            "private_hospital": 0,
            "location_id": 1,
            "created_at": null,
            "updated_at": null
        },
        {
            "id": 2,
            "name": "image",
            "description": "dfnsdknvfksd",
            "locale": "en",
            "is_active": 1,
            "is_approved": 1,
            "doctor_id": 1,
            "general_hospital": 1,
            "private_hospital": 0,
            "location_id": 1,
            "created_at": null,
            "updated_at": null
        },
        {
            "id": 3,
            "name": "image",
            "description": "dfnsdknvfksd",
            "locale": "en",
            "is_active": 1,
            "is_approved": 1,
            "doctor_id": 1,
            "general_hospital": 1,
            "private_hospital": 0,
            "location_id": 1,
            "created_at": null,
            "updated_at": null
        },
        {
            "id": 4,
            "name": "image",
            "description": "dfnsdknvfksd",
            "locale": "en",
            "is_active": 1,
            "is_approved": 1,
            "doctor_id": 1,
            "general_hospital": 1,
            "private_hospital": 0,
            "location_id": 1,
            "created_at": null,
            "updated_at": null
        },
        {
            "id": 5,
            "name": "image",
            "description": "dfnsdknvfksd",
            "locale": "en",
            "is_active": 1,
            "is_approved": 1,
            "doctor_id": 1,
            "general_hospital": 1,
            "private_hospital": 0,
            "location_id": 1,
            "created_at": null,
            "updated_at": null
        },
        {
            "id": 6,
            "name": "image",
            "description": "dfnsdknvfksd",
            "locale": "en",
            "is_active": 1,
            "is_approved": 1,
            "doctor_id": 1,
            "general_hospital": 1,
            "private_hospital": 0,
            "location_id": 1,
            "created_at": null,
            "updated_at": null
        }
    ],
    "specialty": [
        {
            "id": 1,
            "name": "dream",
            "description": "dreamdreamdreamdream",
            "locale": "en",
            "is_active": 1,
            "graduation_year": 1236,
            "created_at": null,
            "updated_at": null
        },
        {
            "id": 2,
            "name": "dream",
            "description": "dreamdreamdreamdream",
            "locale": "en",
            "is_active": 1,
            "graduation_year": 1236,
            "created_at": null,
            "updated_at": null
        },
        {
            "id": 3,
            "name": "dream",
            "description": "dreamdreamdreamdream",
            "locale": "en",
            "is_active": 1,
            "graduation_year": 1236,
            "created_at": null,
            "updated_at": null
        },
        {
            "id": 4,
            "name": "dream",
            "description": "dreamdreamdreamdream",
            "locale": "en",
            "is_active": 1,
            "graduation_year": 1236,
            "created_at": null,
            "updated_at": null
        },
        {
            "id": 5,
            "name": "dream",
            "description": "dreamdreamdreamdream",
            "locale": "en",
            "is_active": 1,
            "graduation_year": 1236,
            "created_at": null,
            "updated_at": null
        },
        {
            "id": 6,
            "name": "dream",
            "description": "dreamdreamdreamdream",
            "locale": "en",
            "is_active": 1,
            "graduation_year": 1236,
            "created_at": null,
            "updated_at": null
        }
    ]
}
